Metadata-Version: 2.1
Name: test-regression-model
Version: 0.0.13
Summary: Example regression model package from Train In Data.
Home-page: https://github.com/trainindata/testing-and-monitoring-ml-deployments
Author: ChristopherGS
Author-email: christopher.samiullah@protonmail.com
License: BSD-3
Classifier: License :: OSI Approved :: MIT License
Classifier: Programming Language :: Python
Classifier: Programming Language :: Python :: 3
Classifier: Programming Language :: Python :: 3.6
Classifier: Programming Language :: Python :: 3.7
Classifier: Programming Language :: Python :: 3.8
Classifier: Programming Language :: Python :: 3.9
Classifier: Programming Language :: Python :: Implementation :: CPython
Classifier: Programming Language :: Python :: Implementation :: PyPy
Requires-Python: >=3.6.0
Requires-Dist: numpy (<1.24.0,>=1.20.0)
Requires-Dist: pandas (<1.6.0,>=1.3.5)
Requires-Dist: pydantic (>=1.9.1)
Requires-Dist: scikit-learn (==1.2.1)
Requires-Dist: strictyaml (<1.4.0,>=1.3.2)
Requires-Dist: ruamel.yaml (==0.16.12)
Requires-Dist: feature-engine (<1.1.0,>=1.0.2)
Requires-Dist: joblib (==1.1.1)
Requires-Dist: kaggle (==1.5.12)
